dbsampler-0.2.2.dist-info/METADATA
dbsampler-0.2.2.dist-info/WHEEL
dbsampler-0.2.2.dist-info/license_files/LICENSE.md
dbsampler/__init__.py
dbsampler/dbsampler.cpython-37m-powerpc64le-linux-gnu.so
dbsampler-0.2.2.dist-info/RECORD
