Metadata-Version: 2.1
Name: dbsampler
Version: 0.2.2
Classifier: Programming Language :: Rust
Classifier: Programming Language :: Python :: Implementation :: CPython
Classifier: Programming Language :: Python :: Implementation :: PyPy
License-File: LICENSE.md
Summary: Decision Boundary Sampler
Author-email: António Leitão <aleitao@novaims.unl.pt>
Requires-Python: >=3.7
Project-URL: repository, https://github.com/antonio-leitao/dbsampler
Project-URL: homepage, https://github.com/antonio-leitao/dbsampler
